cloudgarden/__init__.py
cloudgarden/aws/AwsManager.py
cloudgarden/aws/AwsRegion.py
cloudgarden/aws/AwsResource.py
cloudgarden/aws/resources/DynamoDb.py
cloudgarden/aws/resources/Lambda.py
cloudgarden/aws/resources/Sns.py
cloudgarden/aws/resources/SnsSubscription.py
cloudgarden/aws/resources/Sqs.py
cloudgarden/aws/resources/Stack.py
cloudgarden/diagram/DiagramCellList.py
cloudgarden/diagram/DiagramLink.py
cloudgarden/diagram/DiagramManager.py
cloudgarden/Garden.py
cloudgarden/infrastructure/DiContainer.py
cloudgarden/marshalling/diagram/CellListSchema.py
cloudgarden/marshalling/diagram/CellSchema.py
cloudgarden/marshalling/diagram/ElementSchema.py
cloudgarden/marshalling/diagram/LinkSchema.py
cloudgarden/marshalling/Marshaller.py
cloudgarden-0.1.3.dist-info/WHEEL
cloudgarden-0.1.3.dist-info/METADATA
cloudgarden-0.1.3.dist-info/RECORD
